pyaparat/__init__.py
pyaparat/exceptions.py
pyaparat/main.py
pyaparat/scraper.py
pyaparat-0.0.3.dist-info/LICENSE.txt
pyaparat-0.0.3.dist-info/METADATA
pyaparat-0.0.3.dist-info/WHEEL
pyaparat-0.0.3.dist-info/top_level.txt
pyaparat-0.0.3.dist-info/RECORD
