Metadata-Version: 2.1
Name: pyaparat
Version: 0.0.3
Summary: download aparat.com videos
Home-page: https://github.com/amirbigg/pyaparat
Author: amirhosseing bigdelu
Author-email: amirbig44@gmail.com
License: UNKNOWN
Platform: UNKNOWN
Classifier: Programming Language :: Python :: 3
Classifier: License :: OSI Approved :: MIT License
Classifier: Operating System :: OS Independent
Requires-Python: >=3.6
Requires-Dist: beautifulsoup4
Requires-Dist: requests
